Augmentor/ImageSource.py
Augmentor/ImageUtilities.py
Augmentor/Operations.py
Augmentor/Pipeline.py
Augmentor/__init__.py
Augmentor-0.2.12.dist-info/LICENSE.md
Augmentor-0.2.12.dist-info/METADATA
Augmentor-0.2.12.dist-info/WHEEL
Augmentor-0.2.12.dist-info/top_level.txt
Augmentor-0.2.12.dist-info/RECORD
